zeit/__init__.py
zeit/api.py
zeit/classes.py
zeit/zeit.py
zeit-online/__init__.py
zeit_online-1.0.0.dist-info/LICENSE
zeit_online-1.0.0.dist-info/METADATA
zeit_online-1.0.0.dist-info/WHEEL
zeit_online-1.0.0.dist-info/top_level.txt
zeit_online-1.0.0.dist-info/RECORD
