Metadata-Version: 2.1
Name: zeit-online
Version: 1.0.0
Summary: A Python Wrapper for the Zeit Online Content API
Home-page: https://skriptum.github.io/zeit/
Author: Marten Walk
Author-email: kkx@protonmail.com
License: MIT
Project-URL: Bug Tracker, https://github.com/skriptum/zeit/issues
Project-URL: Documentation, https://github.com/skriptum/zeit/docs
Platform: UNKNOWN
Classifier: Programming Language :: Python :: 3
Classifier: License :: OSI Approved :: MIT License
Classifier: Operating System :: OS Independent
Requires-Python: >=3.6
Requires-Dist: requests (>=2.25.1)
Requires-Dist: pandas (>=1.2.3)
